cabcode/__init__.py
cabcode-0.1.0.dist-info/licenses/LICENSE
cabcode-0.1.0.dist-info/METADATA
cabcode-0.1.0.dist-info/WHEEL
cabcode-0.1.0.dist-info/top_level.txt
cabcode-0.1.0.dist-info/RECORD
