Metadata-Version: 2.4
Name: cabcode
Version: 0.1.0
Summary: CabCode - Python 開發工具套件 | CabLate 的開源專案 | 軟體工程師的技術分享
Author-email: CabLate <your-email@example.com>
License-Expression: MIT
Project-URL: Homepage, https://github.com/yourusername/cabcode
Project-URL: Bug Reports, https://github.com/yourusername/cabcode/issues
Project-URL: Source, https://github.com/yourusername/cabcode
Project-URL: Threads, https://www.threads.com/@cab_late
Project-URL: Author Profile, https://pypi.org/user/CabLate/
Project-URL: Technical Blog, https://www.threads.com/@cab_late
Keywords: cabcode,cablate,python,development,軟體工程,開發工具,技術分享,台灣開發者,開源專案,程式設計
Classifier: Development Status :: 3 - Alpha
Classifier: Intended Audience :: Developers
Classifier: Programming Language :: Python :: 3
Classifier: Programming Language :: Python :: 3.8
Classifier: Programming Language :: Python :: 3.9
Classifier: Programming Language :: Python :: 3.10
Classifier: Programming Language :: Python :: 3.11
Classifier: Programming Language :: Python :: 3.12
Requires-Python: >=3.8
License-File: LICENSE
Dynamic: license-file
